parinvoke/__init__.py
parinvoke/_mp_context.py
parinvoke/_worker.py
parinvoke/config.py
parinvoke/context.py
parinvoke/isolate.py
parinvoke/logging.py
parinvoke/util.py
parinvoke/invoker/__init__.py
parinvoke/invoker/inproc.py
parinvoke/invoker/pool.py
parinvoke/sharing/__init__.py
parinvoke/sharing/_sharedpickle.py
parinvoke/sharing/binpickle.py
parinvoke/sharing/shm.py
parinvoke-0.1.0a5.dist-info/LICENSE.md
parinvoke-0.1.0a5.dist-info/METADATA
parinvoke-0.1.0a5.dist-info/WHEEL
parinvoke-0.1.0a5.dist-info/top_level.txt
parinvoke-0.1.0a5.dist-info/RECORD
