Metadata-Version: 2.1
Name: parinvoke
Version: 0.1.0a5
Summary: Invoke operations on large models in parallel.
Author-email: Michael Ekstrand <mdekstrand@drexel.edu>
License: Copyright (c) 2020–2023 Boise State University
Project-URL: Homepage, https://parinvoke.lenksit.org
Project-URL: GitHub, https://github.com/lenskit/parinvoke
Classifier: License :: OSI Approved :: MIT License
Classifier: Programming Language :: Python :: 3
Classifier: Programming Language :: Python :: 3.10
Classifier: Programming Language :: Python :: 3.11
Classifier: Programming Language :: Python :: 3.12
Classifier: Operating System :: OS Independent
Requires-Python: >=3.10
License-File: LICENSE.md
Requires-Dist: binpickle ~=0.4.0a4
Requires-Dist: seedbank ~=0.2.0a1
Requires-Dist: threadpoolctl >=3.0
Provides-Extra: dev
Requires-Dist: setuptools >=64 ; extra == 'dev'
Requires-Dist: setuptools-scm >=8 ; extra == 'dev'
Requires-Dist: build ; extra == 'dev'
Requires-Dist: twine ; extra == 'dev'
Requires-Dist: ruff ; extra == 'dev'
Requires-Dist: pyright ; extra == 'dev'
Requires-Dist: copier ; extra == 'dev'
Requires-Dist: unbeheader ; extra == 'dev'
Requires-Dist: ipython ; extra == 'dev'
Requires-Dist: pyproject2conda ; extra == 'dev'
Requires-Dist: sphinx-autobuild ; extra == 'dev'
Provides-Extra: doc
Requires-Dist: sphinx >=4.2 ; extra == 'doc'
Requires-Dist: sphinxext-opengraph >=0.5 ; extra == 'doc'
Requires-Dist: furo ; extra == 'doc'
Provides-Extra: test
Requires-Dist: pytest >=7 ; extra == 'test'
Requires-Dist: pytest-cov >=2.12 ; extra == 'test'
Requires-Dist: coverage >=5 ; extra == 'test'
Requires-Dist: numpy >=1.21 ; extra == 'test'
